scrappo/__init__.py
scrappo/app.py
scrappo/downloader.py
scrappo/movies.py
scrappo/processor.py
scrappo/series.py
scrappo/url_parser.py
scrappo/video.py
scrappo/settings/__init__.py
scrappo/settings/manager.py
scrappo/settings/settings.py
scrappo/utils/__init__.py
scrappo/utils/bytes_conversion.py
scrappo/utils/date.py
scrappo/utils/directory.py
scrappo/utils/file.py
scrappo/utils/log.py
scrappo/utils/reflection.py
scrappo/utils/split_string.py
scrappo/utils/yaml.py
scrappo/version/__init__.py
scrappo/version/progsettings.py
scrappo/version/progsettings.yaml
scrappo-1.1.1.dist-info/LICENSE
scrappo-1.1.1.dist-info/METADATA
scrappo-1.1.1.dist-info/WHEEL
scrappo-1.1.1.dist-info/entry_points.txt
scrappo-1.1.1.dist-info/top_level.txt
scrappo-1.1.1.dist-info/RECORD
