Metadata-Version: 2.1
Name: scrappo
Version: 1.1.1
Summary: Download any video from a specific URL.
Home-page: https://github.com/zaytiri/scrappo
Author: zaytiri
Project-URL: GitHub, https://github.com/zaytiri/scrappo
Project-URL: Changelog, https://github.com/zaytiri/scrappo/blob/main/CHANGELOG.md
Keywords: video,download,tool,scrapping,scrap,cli,url python
Classifier: Environment :: Console
Classifier: Intended Audience :: Developers
Classifier: License :: OSI Approved :: MIT License
Classifier: Operating System :: OS Independent
Classifier: Programming Language :: Python :: 3
Requires-Python: >=3.10.6
License-File: LICENSE
Requires-Dist: PyYAML (~=6.0)
Requires-Dist: margument (>=1.1.1)
Requires-Dist: requests (>=2.31.0)
Requires-Dist: progress (~=1.6)
